miru/__init__.py
miru/app.py
miru/interface.py
miru/models.py
miru-0.2.0.dist-info/LICENSE
miru-0.2.0.dist-info/METADATA
miru-0.2.0.dist-info/WHEEL
miru-0.2.0.dist-info/entry_points.txt
miru-0.2.0.dist-info/top_level.txt
miru-0.2.0.dist-info/RECORD
