Metadata-Version: 2.1
Name: miru
Version: 0.2.0
Summary: Utility for keeping track of watched TV episodes and movies.
Home-page: https://soft.github.io/miru/
Author: Samuel Laurén
Author-email: samuel.lauren@iki.fi
License: UNKNOWN
Keywords: log,management,tv,movies,organizer,collection
Platform: UNKNOWN
Classifier: License :: OSI Approved :: GNU General Public License v3 (GPLv3)
Classifier: Environment :: Console :: Curses
Classifier: Intended Audience :: End Users/Desktop
Classifier: Programming Language :: Python :: 3
Classifier: Topic :: Utilities
